Metadata-Version: 1.0
Name: probability-estimation
Version: 0.1
Summary: Gaussian and Binomial distributions
Home-page: UNKNOWN
Author: Richu Thomas
Author-email: richuthomas98@gmail.com
License: UNKNOWN
Platform: UNKNOWN
